cursor_override
