Metadata-Version: 1.1
Name: django-migrate-with-schema-override
Version: 0.4
Summary: Override migrate command not to trip on tables with schema name provided via db_tables.
Home-page: https://github.com/acercado/django-migrate-with-schema-override
Author: Ariel Cercado
Author-email: ariel.cercado@gmail.com
License: MIT
Platform: UNKNOWN
Classifier: Environment :: Web Environment
Classifier: Framework :: Django
Classifier: Intended Audience :: Developers
Classifier: Intended Audience :: System Administrators
Classifier: License :: OSI Approved :: MIT License
Classifier: Operating System :: OS Independent
Classifier: Programming Language :: Python :: 2.7
Classifier: Programming Language :: Python :: 3.5
Classifier: Topic :: Software Development
